LICENSE
README.md
setup.cfg
setup.py
FVS.egg-info/PKG-INFO
FVS.egg-info/SOURCES.txt
FVS.egg-info/dependency_links.txt
FVS.egg-info/entry_points.txt
FVS.egg-info/requires.txt
FVS.egg-info/top_level.txt
fvs/__init__.py
fvs/cli.py
fvs/data.py
fvs/exceptions.py
fvs/file.py
fvs/pattern.py
fvs/repo.py
fvs/state.py
fvs/utils.py