Metadata-Version: 2.1
Name: FVS
Version: 0.2
Summary: File Versioning System with hash comparison, deduplication and data storage to create unlinked states that can be deleted 
Home-page: https://github.com/mirkobrombin/FVS
Author: Mirko Brombin
Author-email: send@mirko.pm
License: MIT
Project-URL: Bug Tracker, https://github.com/mirkobrombin/FVS/issues
Platform: UNKNOWN
Classifier: Programming Language :: Python :: 3
Classifier: License :: OSI Approved :: MIT License
Classifier: Operating System :: POSIX :: Linux
Requires-Python: >=3.9
License-File: LICENSE
